[
  {
    "title": "Sleepwalk",
    "artist": "Santo & Johnny"
  },
  {
    "title": "Still Loving You",
    "artist": "Scorpions"
  },
  {
    "title": "Wind Of Change",
    "artist": "Scorpions"
  },
  {
    "title": "Ya Ves",
    "artist": "Selena"
  },
  {
    "title": "Antología",
    "artist": "Shakira"
  },
  {
    "title": "You're Still The One",
    "artist": "Shania Twain"
  },
  {
    "title": "Tear You Apart",
    "artist": "She Wants Revenge"
  },
  {
    "title": "Seca Tus Lagrimas",
    "artist": "Silvio Brito y Osmel Meriño"
  },
  {
    "title": "Ojala",
    "artist": "Silvio Rodriguez"
  },
  {
    "title": "The Sound of Silence",
    "artist": "Simon & Garfunkel"
  },
  {
    "title": "Don't You (Forget About Me)",
    "artist": "Simple Minds"
  },
  {
    "title": "Entra en Mi Vida",
    "artist": "Sin Bandera"
  },
  {
    "title": "Kilómetros",
    "artist": "Sin Bandera"
  },
  {
    "title": "Que Lloro",
    "artist": "Sin Bandera"
  },
  {
    "title": "Te Vi Venir",
    "artist": "Sin Bandera"
  },
  {
    "title": "Dear Prudence",
    "artist": "Siouxsie & The Banshees"
  },
  {
    "title": "Happy House",
    "artist": "Siouxsie & The Banshees"
  },
  {
    "title": "Spellbound",
    "artist": "Siouxsie & The Banshees"
  },
  {
    "title": "Stargazer",
    "artist": "Siouxsie & The Banshees"
  },
  {
    "title": "Kiss Me",
    "artist": "Sixpence None The Richer"
  }
]